keymapviz/__init__.py
keymapviz/keymapviz.py
keymapviz/legends.py
keymapviz/keyboards/__init__.py
keymapviz/keyboards/crkbd/__init__.py
keymapviz/keyboards/crkbd/layout_editor/default.json
keymapviz/keyboards/dactyl_manuform5x6/__init__.py
keymapviz/keyboards/dactyl_manuform5x6/layout_editor/default.json
keymapviz/keyboards/dactyl_manuform6x6/__init__.py
keymapviz/keyboards/dactyl_manuform6x6/layout_editor/default.json
keymapviz/keyboards/ergo42/__init__.py
keymapviz/keyboards/ergo42/layout_editor/default.json
keymapviz/keyboards/ergodash/__init__.py
keymapviz/keyboards/ergodash/layout_editor/2u_inner.json
keymapviz/keyboards/ergodash/layout_editor/default.json
keymapviz/keyboards/ergodox/__init__.py
keymapviz/keyboards/ergodox/layout_editor/default.json
keymapviz/keyboards/fortitude60/__init__.py
keymapviz/keyboards/fortitude60/layout_editor/default.json
keymapviz/keyboards/helix/__init__.py
keymapviz/keyboards/helix/layout_editor/default.json
keymapviz/keyboards/id75/__init__.py
keymapviz/keyboards/id75/layout_editor/default.json
keymapviz/keyboards/kaishi65/__init__.py
keymapviz/keyboards/kaishi65/layout_editor/default.json
keymapviz/keyboards/kinesis/__init__.py
keymapviz/keyboards/kinesis/layout_editor/default.json
keymapviz/keyboards/kyria/__init__.py
keymapviz/keyboards/kyria/layout_editor/default.json
keymapviz/keyboards/lets_split/__init__.py
keymapviz/keyboards/lets_split/layout_editor/default.json
keymapviz/keyboards/lily58/__init__.py
keymapviz/keyboards/lily58/layout_editor/default.json
keymapviz/keyboards/mint60/__init__.py
keymapviz/keyboards/mint60/layout_editor/default.json
keymapviz/keyboards/moonlander/__init__.py
keymapviz/keyboards/moonlander/layout_editor/default.json
keymapviz/keyboards/planck/__init__.py
keymapviz/keyboards/planck/layout_editor/grid.json
keymapviz/keyboards/planck/layout_editor/mit.json
keymapviz/keyboards/sofle/__init__.py
keymapviz/keyboards/sofle/layout_editor/default.json
keymapviz/keyboards/sweet16/__init__.py
keymapviz-1.14.1.dist-info/LICENSE
keymapviz-1.14.1.dist-info/METADATA
keymapviz-1.14.1.dist-info/WHEEL
keymapviz-1.14.1.dist-info/entry_points.txt
keymapviz-1.14.1.dist-info/top_level.txt
keymapviz-1.14.1.dist-info/RECORD
