Metadata-Version: 2.1
Name: keymapviz
Version: 1.14.1
Summary: keymap.c visualizer
Home-page: https://github.com/yskoht/keymapviz
Author: yskoht
Author-email: ysk.oht@gmail.com
License: UNKNOWN
Project-URL: Bug Reports, https://github.com/yskoht/keymapviz/issues
Project-URL: Source, https://github.com/yskoht/keymapviz
Keywords: keymapviz keymap.c qmk_firmware
Platform: UNKNOWN
Classifier: License :: OSI Approved :: MIT License
Classifier: Programming Language :: Python :: 3.5
Classifier: Programming Language :: Python :: 3.6
Classifier: Programming Language :: Python :: 3.7
Requires-Python: >=3.5
Requires-Dist: regex
